corcli/__init__.py
corcli/__main__.py
corcli/analyzer.py
corcli/cortex.py
corcli-1.1.0.dist-info/LICENSE
corcli-1.1.0.dist-info/METADATA
corcli-1.1.0.dist-info/WHEEL
corcli-1.1.0.dist-info/entry_points.txt
corcli-1.1.0.dist-info/top_level.txt
corcli-1.1.0.dist-info/RECORD
