Metadata-Version: 2.1
Name: corcli
Version: 1.1.0
Summary: A simple CLI client for Cortex
Home-page: https://github.com/0xFustang/corcli
Author: 0xFustang
Author-email: 0xFustang@proton.me
Requires-Python: >=3.9
License-File: LICENSE
Requires-Dist: inquirer ==3.1.3
Requires-Dist: cortex4py ==2.1.0
Requires-Dist: colorama ==0.4.6
Requires-Dist: toml ==0.10.2
